strava_to_sqlite/__init__.py
strava_to_sqlite/cli.py
strava_to_sqlite/utils.py
strava_to_sqlite-0.1.1.dist-info/LICENSE
strava_to_sqlite-0.1.1.dist-info/METADATA
strava_to_sqlite-0.1.1.dist-info/WHEEL
strava_to_sqlite-0.1.1.dist-info/entry_points.txt
strava_to_sqlite-0.1.1.dist-info/RECORD
