Metadata-Version: 2.1
Name: strava-to-sqlite
Version: 0.1.1
Summary: Create a SQLite database containing data pulled from Strava
License: MIT
Author: Hrishikesh Barman
Author-email: oss@geekodour.org
Requires-Python: >=3.11,<4.0
Classifier: License :: OSI Approved :: MIT License
Classifier: Programming Language :: Python :: 3
Classifier: Programming Language :: Python :: 3.11
Classifier: Programming Language :: Python :: 3.12
Requires-Dist: click (>=8.1.7,<9.0.0)
Requires-Dist: pydantic (>=2.5.2,<3.0.0)
Requires-Dist: requests (>=2.31.0,<3.0.0)
Requires-Dist: sqlite-utils (>=3.36,<4.0)
Requires-Dist: structlog (>=23.1.0,<24.0.0)
